taash/__init__.py
taash/_modidx.py
taash/card.py
taash/deck.py
taash-0.0.1.dist-info/LICENSE
taash-0.0.1.dist-info/METADATA
taash-0.0.1.dist-info/WHEEL
taash-0.0.1.dist-info/entry_points.txt
taash-0.0.1.dist-info/top_level.txt
taash-0.0.1.dist-info/RECORD
