Metadata-Version: 2.1
Name: taash
Version: 0.0.1
Summary: A deck of cards demo of [nbdev](https://nbdev.fast.ai)
Home-page: https://github.com/nasheqlbrm/taash
Author: Kaushik Sinha
Author-email: nasheqlbrm@users.noreply.github.com
License: Apache Software License 2.0
Keywords: nbdev jupyter notebook python
Classifier: Development Status :: 4 - Beta
Classifier: Intended Audience :: Developers
Classifier: Natural Language :: English
Classifier: Programming Language :: Python :: 3.7
Classifier: Programming Language :: Python :: 3.8
Classifier: Programming Language :: Python :: 3.9
Classifier: Programming Language :: Python :: 3.10
Classifier: License :: OSI Approved :: Apache Software License
Requires-Python: >=3.7
License-File: LICENSE
Provides-Extra: dev
